buckfit/__init__.py
buckfit/atom_types.py
buckfit/atoms.py
buckfit/bond_types.py
buckfit/bonds.py
buckfit/collate_structures.py
buckfit/cross_validation.py
buckfit/fitting_code.py
buckfit/fitting_output.py
buckfit/from_structure.py
buckfit/input_checker.py
buckfit/lammps_data.py
buckfit/lattice_parameters.py
buckfit/plotting.py
buckfit/potential_parameters.py
buckfit/potentials.py
popoff/__init__.py
popoff/atom_types.py
popoff/atoms.py
popoff/bond_types.py
popoff/bonds.py
popoff/collate_structures.py
popoff/cross_validation.py
popoff/fitting_code.py
popoff/fitting_output.py
popoff/from_structure.py
popoff/input_checker.py
popoff/lammps_data.py
popoff/lattice_parameters.py
popoff/plotting.py
popoff/potential_parameters.py
popoff/potentials.py
PopOff-0.0.1.dist-info/LICENSE
PopOff-0.0.1.dist-info/METADATA
PopOff-0.0.1.dist-info/WHEEL
PopOff-0.0.1.dist-info/top_level.txt
PopOff-0.0.1.dist-info/RECORD
