Metadata-Version: 2.1
Name: PopOff
Version: 0.0.1
Summary: POPOFF: POtential Parameter Optimisation for Force-Fields
Home-page: https://github.com/LMMorgan/PopOff
Author: Lucy M. Morgan
Author-email: l.m.morgan@bath.ac.uk
License: MIT
Platform: UNKNOWN
Requires-Dist: pymatgen (>=v2017.10.16)
Requires-Dist: numpy
Requires-Dist: Cython (>=0.29.9)
Requires-Dist: lammps-cython (==0.5.8)
Requires-Dist: matplotlib (>=3.1.0)
Requires-Dist: scipy
Requires-Dist: seaborn (>=0.9.0)
Requires-Dist: pytest
